{
  "project_info": {
    "project_number": "900838497953",
    "project_id": "nomadic-sublime-229102",
    "storage_bucket": "nomadic-sublime-229102.appspot.com"
  },
  "client": [
    {
      "client_info": {
        "mobilesdk_app_id": "1:900838497953:android:6738185d1a0ab140431ae0",
        "android_client_info": {
          "package_name": "com.onethinklogic.doamuslim"
        }
      },
      "oauth_client": [
        {
          "client_id": "900838497953-ohbdjgrqm11r8g0b1rvsq4q4bi29bebo.apps.googleusercontent.com",
          "client_type": 1,
          "android_info": {
            "package_name": "com.onethinklogic.doamuslim",
            "certificate_hash": "4da8c1e2c3a1169016411e0e28c7786efb33411c"
          }
        },
        {
          "client_id": "900838497953-j1cdafbt1b5indfhru9abntlr7nodrru.apps.googleusercontent.com",
          "client_type": 3
        }
      ],
      "api_key": [
        {
          "current_key": "AIzaSyA5Mr2MC4OlhE_oGRjBjnuouMf_fCpG1-U"
        }
      ],
      "services": {
        "appinvite_service": {
          "other_platform_oauth_client": [
            {
              "client_id": "900838497953-j1cdafbt1b5indfhru9abntlr7nodrru.apps.googleusercontent.com",
              "client_type": 3
            }
          ]
        }
      }
    }
  ],
  "configuration_version": "1"
}